README.rst
setup.py
ctypes_ftdi1.egg-info/PKG-INFO
ctypes_ftdi1.egg-info/SOURCES.txt
ctypes_ftdi1.egg-info/dependency_links.txt
ctypes_ftdi1.egg-info/top_level.txt
ftdi1/__init__.py
ftdi1/_ftdi1.py
ftdi1/ftdi1.py