Metadata-Version: 1.1
Name: ctypes-ftdi1
Version: 0.0.4
Summary: libftdi1 python bindings based on ctypes
Home-page: https://github.com/soburi/ctypes-ftdi1
Author: Tokita Hiroshi
Author-email: tokita.hiroshi@gmail.com
License: MIT
Platform: any
Classifier: Programming Language :: Python
Classifier: License :: OSI Approved :: MIT License
Classifier: Operating System :: OS Independent
Classifier: Topic :: System :: Hardware :: Hardware Drivers
